LICENSE.txt
README.md
setup.cfg
setup.py
fittingNURBS/__init__.py
fittingNURBS/core.py
fittingNURBS.egg-info/PKG-INFO
fittingNURBS.egg-info/SOURCES.txt
fittingNURBS.egg-info/dependency_links.txt
fittingNURBS.egg-info/top_level.txt