Metadata-Version: 2.1
Name: fittingNURBS
Version: 0.1
Summary: fitting test
Author: aiolosgs
Author-email: aiolosgs@1633.com
License: MIT
Classifier: Development Status :: 3 - Alpha
Classifier: Intended Audience :: Developers
Classifier: Topic :: Software Development :: Build Tools
Classifier: License :: OSI Approved :: MIT License
Classifier: Programming Language :: Python :: 3.7
License-File: LICENSE.txt
